userstats/__init__.py
userstats/__main__.py
userstats/_database_additions.py.bak
userstats/activity_tracker.py
userstats/database.py
userstats/emote_detector.py
userstats/kudos_detector.py
userstats/main.py
userstats/metrics_server.py
userstats/nats_publisher.py
kryten_userstats-0.6.0.dist-info/METADATA
kryten_userstats-0.6.0.dist-info/WHEEL
kryten_userstats-0.6.0.dist-info/entry_points.txt
kryten_userstats-0.6.0.dist-info/licenses/LICENSE
kryten_userstats-0.6.0.dist-info/RECORD
