Metadata-Version: 2.4
Name: kryten-userstats
Version: 0.6.0
Summary: User statistics tracking microservice for CyTube channels
Author-email: Your Name <your.email@example.com>
License: MIT
License-File: LICENSE
Keywords: cytube,microservice,nats,prometheus,statistics,tracking
Classifier: Development Status :: 4 - Beta
Classifier: Intended Audience :: Developers
Classifier: License :: OSI Approved :: MIT License
Classifier: Programming Language :: Python :: 3
Classifier: Programming Language :: Python :: 3.10
Classifier: Programming Language :: Python :: 3.11
Classifier: Programming Language :: Python :: 3.12
Classifier: Topic :: Communications :: Chat
Classifier: Topic :: Software Development :: Libraries :: Python Modules
Requires-Python: <4.0.0,>=3.10
Requires-Dist: aiohttp<4.0.0,>=3.9.0
Requires-Dist: kryten-py>=0.9.10
